MANIFEST.in
README.rst
setup.py
sentry_phabricator/__init__.py
sentry_phabricator/models.py
sentry_phabricator/plugin.py
sentry_phabricator.egg-info/PKG-INFO
sentry_phabricator.egg-info/SOURCES.txt
sentry_phabricator.egg-info/dependency_links.txt
sentry_phabricator.egg-info/entry_points.txt
sentry_phabricator.egg-info/not-zip-safe
sentry_phabricator.egg-info/requires.txt
sentry_phabricator.egg-info/top_level.txt