Metadata-Version: 1.0
Name: sentry-phabricator
Version: 0.6.2
Summary: A Sentry extension which integrates with Phabricator.
Home-page: http://github.com/getsentry/sentry-phabricator
Author: David Cramer
Author-email: dcramer@gmail.com
License: BSD
Platform: UNKNOWN
Classifier: Framework :: Django
Classifier: Intended Audience :: Developers
Classifier: Intended Audience :: System Administrators
Classifier: Operating System :: OS Independent
Classifier: Topic :: Software Development
